ffmpeg_asyncio/__init__.py
ffmpeg_asyncio/ffmpeg.py
ffmpeg_asyncio/file.py
ffmpeg_asyncio/options.py
ffmpeg_asyncio/progress.py
ffmpeg_asyncio/protocol.py
ffmpeg_asyncio/stats.py
ffmpeg_asyncio/types.py
ffmpeg_asyncio/utils.py
ffmpeg_asyncio-0.1.3.dist-info/LICENSE
ffmpeg_asyncio-0.1.3.dist-info/METADATA
ffmpeg_asyncio-0.1.3.dist-info/WHEEL
ffmpeg_asyncio-0.1.3.dist-info/top_level.txt
ffmpeg_asyncio-0.1.3.dist-info/RECORD
