Metadata-Version: 2.1
Name: ffmpeg-asyncio
Version: 0.1.3
Summary: A fork of the excellent python-ffmpeg binding for FFmpeg, updated for native async API support only.
Author: Bruce Cutler
Author-email: Bruce Cutler <bruce@sumebrius.net>
License: Copyright 2023 Bruce Cutler
Keywords: ffmpeg,asyncio
Classifier: License :: OSI Approved :: MIT License
Classifier: Programming Language :: Python
Classifier: Programming Language :: Python :: 3
Requires-Python: >=3.6
License-File: LICENSE
Requires-Dist: pyee
Requires-Dist: typing-extensions
